aiostem/__init__.py
aiostem/command.py
aiostem/connector.py
aiostem/controller.py
aiostem/event.py
aiostem/exceptions.py
aiostem/monitor.py
aiostem/py.typed
aiostem/reply.py
aiostem/structures.py
aiostem/types.py
aiostem/version.py
aiostem/utils/__init__.py
aiostem/utils/argument.py
aiostem/utils/backports.py
aiostem/utils/encoding.py
aiostem/utils/message.py
aiostem/utils/syntax.py
aiostem/utils/transformers.py
aiostem-0.4.6.dist-info/licenses/LICENSE
aiostem-0.4.6.dist-info/METADATA
aiostem-0.4.6.dist-info/WHEEL
aiostem-0.4.6.dist-info/top_level.txt
aiostem-0.4.6.dist-info/RECORD
