Metadata-Version: 2.4
Name: aiostem
Version: 0.4.6
Summary: Asynchronous Tor controller library for asyncio and Python
Author-email: Romain Bezut <morian@xdec.net>
Project-URL: Changelog, https://github.com/morian/aiostem/blob/master/CHANGELOG.rst
Project-URL: Coverage, https://app.codecov.io/github/morian/aiostem
Project-URL: Documentation, https://aiostem.readthedocs.io
Project-URL: Homepage, https://pypi.org/project/aiostem/
Project-URL: Issues, https://github.com/morian/aiostem/issues
Project-URL: Repository, https://github.com/morian/aiostem
Classifier: Framework :: AsyncIO
Classifier: Framework :: Pydantic :: 2
Classifier: Intended Audience :: Developers
Classifier: Intended Audience :: Information Technology
Classifier: License :: OSI Approved :: MIT License
Classifier: Operating System :: POSIX :: Linux
Classifier: Programming Language :: Python
Classifier: Programming Language :: Python :: 3
Classifier: Programming Language :: Python :: 3 :: Only
Classifier: Programming Language :: Python :: 3.10
Classifier: Programming Language :: Python :: 3.11
Classifier: Programming Language :: Python :: 3.12
Classifier: Programming Language :: Python :: 3.13
Classifier: Programming Language :: Python :: 3.14
Classifier: Topic :: Software Development :: Libraries :: Python Modules
Classifier: Typing :: Typed
Requires-Python: >=3.10
License-File: LICENSE
Requires-Dist: cryptography<47.0,>=44.0
Requires-Dist: pydantic<3.0,>=2.9
Requires-Dist: typing_extensions>4.0; python_version < "3.11"
Dynamic: license-file
